{
  "guruvigneshy-design-control-consultant-100-matching-1784554517.docx": {
    "original": "GuruvigneshY_Design Control Consultant_100% Matching.docx",
    "source": "zip",
    "zip_name": "Design Control Consultant Resume.zip",
    "uploaded_at": "2026-07-20 19:05",
    "parsed": true,
    "resume_id": 103
  },
  "maltheshkarnam-design-control-7y-0m-2-1784554517.pdf": {
    "original": "MaltheshKarnam_Design Control_[7y_0m] (2).pdf",
    "source": "zip",
    "zip_name": "Design Control Consultant Resume.zip",
    "uploaded_at": "2026-07-20 19:05",
    "parsed": true,
    "resume_id": 104
  },
  "manibharathir-design-control-5y-6m-1-1784554517.pdf": {
    "original": "ManiBharathiR_Design Control_[5y_6m] (1).pdf",
    "source": "zip",
    "zip_name": "Design Control Consultant Resume.zip",
    "uploaded_at": "2026-07-20 19:05",
    "parsed": true,
    "resume_id": 105
  },
  "nanthakumar-design-control-consultant-30-matching-1784554517.docx": {
    "original": "Nanthakumar_Design Control Consultant_30% Matching.docx",
    "source": "zip",
    "zip_name": "Design Control Consultant Resume.zip",
    "uploaded_at": "2026-07-20 19:05",
    "parsed": true,
    "resume_id": 106
  },
  "naukri-vishwanathhiremath-8y-0m-1784554517.docx": {
    "original": "Naukri_VISHWANATHHIREMATH[8y_0m].docx",
    "source": "zip",
    "zip_name": "Design Control Consultant Resume.zip",
    "uploaded_at": "2026-07-20 19:05",
    "parsed": true,
    "resume_id": 107
  },
  "ravikumar-profile-design-control-consultant-50-matching-1784554517.docx": {
    "original": "Ravikumar Profile_Design Control Consultant_50% Matching.docx",
    "source": "zip",
    "zip_name": "Design Control Consultant Resume.zip",
    "uploaded_at": "2026-07-20 19:05",
    "parsed": true,
    "resume_id": 108
  },
  "selvasubramaninaanand-design-control-9y-0m-1784554517.docx": {
    "original": "Selvasubramaninaanand_Design Control_[9y_0m].docx",
    "source": "zip",
    "zip_name": "Design Control Consultant Resume.zip",
    "uploaded_at": "2026-07-20 19:05",
    "parsed": true,
    "resume_id": 109
  },
  "sivaranjanid-design-control-5y-2m-1-1784554517.pdf": {
    "original": "SivaranjaniD_Design Control_[5y_2m] (1).pdf",
    "source": "zip",
    "zip_name": "Design Control Consultant Resume.zip",
    "uploaded_at": "2026-07-20 19:05",
    "parsed": true,
    "resume_id": 110
  },
  "suresh-design-control-consultant-10-matching-1784554517.docx": {
    "original": "Suresh_Design Control Consultant_10% Matching.docx",
    "source": "zip",
    "zip_name": "Design Control Consultant Resume.zip",
    "uploaded_at": "2026-07-20 19:05",
    "parsed": true,
    "resume_id": 111
  },
  "abhisheak-cv-csv-analyst-1-1784554560.pdf": {
    "original": "Abhisheak_CV_CSV Analyst (1).pdf",
    "source": "zip",
    "zip_name": "Vaisesika Resume.zip",
    "uploaded_at": "2026-07-20 19:06",
    "parsed": true,
    "resume_id": 112
  },
  "afreen-nikhath-sqa-1784554560.docx": {
    "original": "Afreen Nikhath_SQA.docx",
    "source": "zip",
    "zip_name": "Vaisesika Resume.zip",
    "uploaded_at": "2026-07-20 19:06",
    "parsed": true,
    "resume_id": 113
  },
  "arun-sivakumar-1784554560.pdf": {
    "original": "arun-sivakumar.pdf",
    "source": "zip",
    "zip_name": "Vaisesika Resume.zip",
    "uploaded_at": "2026-07-20 19:06",
    "parsed": true,
    "resume_id": 114
  },
  "josephjamesamalan-prs-13y-0m-9627732446533772583-1784554560.docx": {
    "original": "JosephJamesAmalan_PRS _[13y_0m]_9627732446533772583.docx",
    "source": "zip",
    "zip_name": "Vaisesika Resume.zip",
    "uploaded_at": "2026-07-20 19:06",
    "parsed": true,
    "resume_id": 115
  },
  "santhoshkumar-sqa-7y-1m-1-1784554560.pdf": {
    "original": "Santhoshkumar_SQA_[7y_1m] 1.pdf",
    "source": "zip",
    "zip_name": "Vaisesika Resume.zip",
    "uploaded_at": "2026-07-20 19:06",
    "parsed": true,
    "resume_id": 116
  },
  "satheesh-kumar-1781381823-1784554560.docx": {
    "original": "satheesh-kumar-1781381823.docx",
    "source": "zip",
    "zip_name": "Vaisesika Resume.zip",
    "uploaded_at": "2026-07-20 19:06",
    "parsed": true,
    "resume_id": 117
  }
}